gitreg/__init__.py
gitreg/main.py
gitreg-0.0.1.dist-info/LICENSE
gitreg-0.0.1.dist-info/METADATA
gitreg-0.0.1.dist-info/WHEEL
gitreg-0.0.1.dist-info/top_level.txt
gitreg-0.0.1.dist-info/RECORD
