Metadata-Version: 2.1
Name: gitreg
Version: 0.0.1
Summary: Gitreg
Home-page: https://gitreg.com/
Author: Maxime Logé
Author-email: maxime.loge@gitreg.com
Project-URL: Bug Tracker, https://gitreg.com/issues
Classifier: Programming Language :: Python :: 3
Classifier: License :: OSI Approved :: MIT License
Classifier: Operating System :: OS Independent
Requires-Python: >=3.6
License-File: LICENSE
